edaeasy/__init__.py
edaeasy/config.toml
edaeasy/functions.py
edaeasy/preprocessing.py
edaeasy-1.2.9.dist-info/LICENSE
edaeasy-1.2.9.dist-info/METADATA
edaeasy-1.2.9.dist-info/WHEEL
edaeasy-1.2.9.dist-info/RECORD
