Metadata-Version: 2.1
Name: EDAeasy
Version: 1.2.9
Summary: Functions and tools for making Exploratory Data Analysis easy!
License: MIT
Keywords: Exploratory Analysis,EDA
Author: Francisco Jesus Ocazionez Cardozo
Author-email: pach812@gmail.com
Requires-Python: >=3.9,<4.0
Classifier: License :: OSI Approved :: MIT License
Classifier: Programming Language :: Python :: 3
Classifier: Programming Language :: Python :: 3.9
Classifier: Programming Language :: Python :: 3.10
Classifier: Programming Language :: Python :: 3.11
Requires-Dist: jinja2 (>=3.1.4,<4.0.0)
Requires-Dist: numpy (>=1.24.0,<2.0.0)
Requires-Dist: pandas (>=1.5.0)
Requires-Dist: pingouin (>=0.5.4,<0.6.0)
Requires-Dist: pytest (>=8.2.2,<9.0.0)
Requires-Dist: pytest-mock (>=3.14.0,<4.0.0)
Requires-Dist: python-docx (>=1.1.2,<2.0.0)
Requires-Dist: statsmodels (>=0.14.2,<0.15.0)
